.gitignore
.travis.yml
CHANGELOG.rst
LICENSE-MIT
MANIFEST.in
README.rst
requirements-dev.txt
requirements.txt
setup.py
test.sh
flask_json_multidict/__init__.py
flask_json_multidict/__init__.pyc
flask_json_multidict/flask_json_multidict.py
flask_json_multidict/flask_json_multidict.pyc
flask_json_multidict.egg-info/PKG-INFO
flask_json_multidict.egg-info/SOURCES.txt
flask_json_multidict.egg-info/dependency_links.txt
flask_json_multidict.egg-info/pbr.json
flask_json_multidict.egg-info/requires.txt
flask_json_multidict.egg-info/top_level.txt
flask_json_multidict/__pycache__/__init__.cpython-34.pyc
flask_json_multidict/__pycache__/flask_json_multidict.cpython-34.pyc
flask_json_multidict/test/__init__.py
flask_json_multidict/test/__init__.pyc
flask_json_multidict/test/test.py
flask_json_multidict/test/test.pyc
flask_json_multidict/test/__pycache__/__init__.cpython-34.pyc
flask_json_multidict/test/__pycache__/test.cpython-34.pyc
flask_json_multidict/test/utils/__init__.py
flask_json_multidict/test/utils/__init__.pyc
flask_json_multidict/test/utils/test_server.py
flask_json_multidict/test/utils/test_server.pyc
flask_json_multidict/test/utils/__pycache__/__init__.cpython-34.pyc
flask_json_multidict/test/utils/__pycache__/test_server.cpython-34.pyc