Metadata-Version: 1.1
Name: flask-json-multidict
Version: 1.0.0
Summary: Convert Flask's `request.get_json` dict into a MultiDict like `request.form`
Home-page: https://github.com/underdogio/flask-json-multidict
Author: Todd Wolfson
Author-email: todd@twolfson.com
License: MIT
Download-URL: https://github.com/underdogio/flask-json-multidict/archive/master.zip
Keywords: flask,request,json,multidict,form
Platform: UNKNOWN
Classifier: Development Status :: 3 - Alpha
Classifier: Framework :: Flask
Classifier: Intended Audience :: Developers
Classifier: License :: OSI Approved :: MIT License
Classifier: Operating System :: OS Independent
Classifier: Programming Language :: Python
